ec_metrics/__init__.py
ec_metrics/__main__.py
ec_metrics-0.3.dist-info/METADATA
ec_metrics-0.3.dist-info/WHEEL
ec_metrics-0.3.dist-info/entry_points.txt
ec_metrics-0.3.dist-info/top_level.txt
ec_metrics-0.3.dist-info/RECORD
