Metadata-Version: 2.1
Name: ec_metrics
Version: 0.3
Summary: Пакет для расчета чистой прибыли и рентабельности инвестиций (ROI).
Home-page: https://github.com/yourusername/finance_metrics
Author: Анастасия Колесникова
Classifier: Programming Language :: Python :: 3
Classifier: License :: OSI Approved :: MIT License
Classifier: Operating System :: OS Independent
Requires-Python: >=3.6
